git_mcp/__init__.py
git_mcp/server.py
git_mcp-0.3.2.dist-info/METADATA
git_mcp-0.3.2.dist-info/WHEEL
git_mcp-0.3.2.dist-info/entry_points.txt
git_mcp-0.3.2.dist-info/top_level.txt
git_mcp-0.3.2.dist-info/RECORD
