Metadata-Version: 2.2
Name: git-mcp
Version: 0.3.2
Summary: MCP server for managing Git operations
Author: Kristof Jozsa
Project-URL: Repository, https://github.com/kjozsa/git-mcp
Requires-Python: >=3.10
Requires-Dist: fastmcp
Requires-Dist: loguru
Requires-Dist: python-dotenv
